{
  "parent": "moonbits:recipes/root",
  "rewards": {
    "recipes": [
      "moonbits:storage_blocks/paper_bundle",
      "moonbits:storage_blocks/paper_from_bundle"
    ]
  },
  "criteria": {
    "has_paper": {
      "trigger": "minecraft:inventory_changed",
      "conditions": {
        "items": [
          {
            "item": "minecraft:paper"
          }
        ]
      }
    },
    "has_the_recipe": {
      "trigger": "minecraft:recipe_unlocked",
      "conditions": {
        "recipe": "moonbits:storage_blocks/paper_bundle"
      }
    }
  },
  "requirements": [
    [
      "has_paper",
      "has_the_recipe"
    ]
  ]
}